__init__.py
atas_client/CoreATASApi.py
atas_client/HttpUtil.py
atas_client/__init__.py
atas_client/atas_client.py
atas_client-1.0.1.dist-info/LICENSE
atas_client-1.0.1.dist-info/METADATA
atas_client-1.0.1.dist-info/WHEEL
atas_client-1.0.1.dist-info/top_level.txt
atas_client-1.0.1.dist-info/RECORD
