Metadata-Version: 2.1
Name: atas_client
Version: 1.0.1
Summary: ATAS Automation API
Author-email: "tao.ding" <tao.ding@rakuten.com>
License: Copyright (c) 2018 The Python Packaging Authority
Project-URL: Homepage, https://github.com
Project-URL: Bug Tracker, https://github.com
Classifier: Programming Language :: Python :: 3
Classifier: License :: OSI Approved :: MIT License
Classifier: Operating System :: OS Independent
Requires-Python: >=3.7
License-File: LICENSE
